[
null,
{"id":1,"animationId":41,"consumable":true,"damage":{"critical":false,"elementId":0,"formula":"0","type":0,"variance":20},"description":"har har harhar har harharharharhar","effects":[{"code":11,"dataId":0,"value1":0,"value2":100}],"hitType":0,"iconIndex":176,"itypeId":1,"name":"Freddy Fazbear's Pizza","note":"","occasion":0,"price":30,"repeats":1,"scope":7,"speed":0,"successRate":100,"tpGain":0},
{"id":2,"animationId":41,"consumable":true,"damage":{"critical":false,"elementId":0,"formula":"0","type":0,"variance":20},"description":"Feed it to your camel so its cooler for 10 turns","effects":[{"code":31,"dataId":6,"value1":10,"value2":0}],"hitType":0,"iconIndex":176,"itypeId":1,"name":"Camel Feed","note":"","occasion":0,"price":5,"repeats":1,"scope":7,"speed":100,"successRate":100,"tpGain":0},
{"id":3,"animationId":45,"consumable":true,"damage":{"critical":false,"elementId":0,"formula":"0","type":0,"variance":20},"description":"Gives you a random quote.","effects":[{"code":22,"dataId":4,"value1":1,"value2":0},{"code":22,"dataId":5,"value1":1,"value2":0},{"code":22,"dataId":6,"value1":1,"value2":0},{"code":22,"dataId":7,"value1":1,"value2":0},{"code":22,"dataId":8,"value1":1,"value2":0},{"code":22,"dataId":9,"value1":1,"value2":0},{"code":22,"dataId":10,"value1":1,"value2":0}],"hitType":0,"iconIndex":176,"itypeId":2,"name":"Urim","note":"","occasion":0,"price":200,"repeats":1,"scope":7,"speed":0,"successRate":100,"tpGain":0},
{"id":4,"animationId":49,"consumable":true,"damage":{"critical":false,"elementId":0,"formula":"b.mhp / 2","type":3,"variance":20},"description":"Gives you an Albert Einstien quote from 1894.","effects":[{"code":22,"dataId":1,"value1":1,"value2":0}],"hitType":0,"iconIndex":176,"itypeId":2,"name":"Thummim","note":"","occasion":0,"price":300,"repeats":1,"scope":9,"speed":0,"successRate":100,"tpGain":0},
{"id":5,"animationId":0,"consumable":false,"damage":{"critical":false,"elementId":0,"formula":"0","type":0,"variance":20},"description":"teaches yalls about alchemy","effects":[],"hitType":0,"iconIndex":0,"itypeId":2,"name":"Alchemy Book","note":"","occasion":0,"price":0,"repeats":1,"scope":7,"speed":0,"successRate":0,"tpGain":0},
{"id":6,"animationId":0,"consumable":true,"damage":{"critical":false,"elementId":0,"formula":"0","type":0,"variance":20},"description":"You get a nice friend (worth it)","effects":[],"hitType":0,"iconIndex":0,"itypeId":1,"name":"Freddy Fazfriend","note":"","occasion":0,"price":1000,"repeats":1,"scope":7,"speed":0,"successRate":100,"tpGain":0}
]